LICENSE
MANIFEST.in
README.md
setup.cfg
setup.py
versioneer.py
./.gitattributes
./CODE_OF_CONDUCT.md
./CONTRIBUTING.md
./Dockerfile
./LICENSE
./MANIFEST.in
./README.md
./setup.cfg
./setup.py
./versioneer.py
./mailutility/__init__.py
./mailutility/_version.py
./mailutility/mailmonitor.py
./mailutility/mailsender.py
./mailutility.egg-info/PKG-INFO
./mailutility.egg-info/SOURCES.txt
./mailutility.egg-info/dependency_links.txt
./mailutility.egg-info/requires.txt
./mailutility.egg-info/top_level.txt
mailutility/__init__.py
mailutility/_version.py
mailutility/mailmonitor.py
mailutility/mailsender.py
mailutility.egg-info/PKG-INFO
mailutility.egg-info/SOURCES.txt
mailutility.egg-info/dependency_links.txt
mailutility.egg-info/requires.txt
mailutility.egg-info/top_level.txt