Metadata-Version: 2.1
Name: mailutility
Version: 0.1.81
Summary: A package containing a tool to send mail and a tool to monitor a mailbox easily
Home-page: https://github.com/Advestis/mailutility
Author: Advestis
Author-email: pythondev@advestis.com
License: GPLv3
Project-URL: Bug Tracker, https://github.com/Advestis/mailutility/issues
Project-URL: Documentation, https://advestis.github.io/mailutility
Project-URL: Source Code, https://github.com/Advestis/mailutility/
Platform: UNKNOWN
Classifier: Development Status :: 5 - Production/Stable
Classifier: License :: OSI Approved :: GNU General Public License v3 (GPLv3)
Classifier: Operating System :: Unix
Classifier: Programming Language :: Python :: 3.7
Classifier: Programming Language :: Python :: 3.8
Classifier: Programming Language :: Python :: 3.9
Requires-Python: >=3.7
License-File: LICENSE
